CHANGELOG.rst
LICENSE
MANIFEST.in
README.rst
setup.py
tox.ini
demo_site/manage.py
demo_site/demo_site/__init__.py
demo_site/demo_site/auth.py
demo_site/demo_site/settings.py
demo_site/demo_site/urls.py
demo_site/demo_site/views.py
demo_site/demo_site/wsgi.py
demo_site/upload/__init__.py
demo_site/upload/admin.py
demo_site/upload/apps.py
demo_site/upload/models.py
demo_site/upload/tests.py
demo_site/upload/views.py
demo_site/upload/migrations/__init__.py
django_oss_storage/__init__.py
django_oss_storage/backends.py
django_oss_storage/defaults.py
livingbio_django_oss_storage.egg-info/PKG-INFO
livingbio_django_oss_storage.egg-info/SOURCES.txt
livingbio_django_oss_storage.egg-info/dependency_links.txt
livingbio_django_oss_storage.egg-info/requires.txt
livingbio_django_oss_storage.egg-info/top_level.txt
tests/manage.py
tests/django-oss-storage-test/__init__.py
tests/django-oss-storage-test/settings.py
tests/django-oss-storage-test/tests.py